.DS_Store
tests/__init__.py
tests/test_unipass.py
unipass/__init__.py
unipass/api.py
unipass-0.1.dist-info/LICENSE
unipass-0.1.dist-info/METADATA
unipass-0.1.dist-info/WHEEL
unipass-0.1.dist-info/top_level.txt
unipass-0.1.dist-info/RECORD
