Metadata-Version: 2.1
Name: unipass
Version: 0.1
Summary: Korean custom unipass OpenAPI wrapper
Home-page: http://github.com/bandoche/unipass
Author: Sangjun Jung
Author-email: bandoche@hanmail.net
License: MIT
Platform: UNKNOWN
Classifier: Development Status :: 4 - Beta
Classifier: Environment :: Console
Classifier: License :: OSI Approved :: MIT License
Classifier: Operating System :: OS Independent
Classifier: Programming Language :: Python :: 3 :: Only
Classifier: Programming Language :: Python :: 3.9
Requires-Dist: httpx (==0.16.1)
